{
    "classname": "SimpleHeader",
    "definitions": {
        "apis": {
            "custom": [],
            "passthrough": []
        },
        "events": {
            "custom": [],
            "passthrough": [
                {
                    "access": "Enable",
                    "group": "General",
                    "kuid": "f49d5eb03c814116aa69458c7af4e4e2",
                    "originalPropertyKey": "onClick",
                    "propertyIndex": 1,
                    "propertyKey": "onClickLeft",
                    "pw": {
                        "access": "readwrite",
                        "category": "action",
                        "displayName": "onClickLeft",
                        "srcWidget": "flxIconLeft",
                        "type": "action",
                        "uiRepresentation": "Label-Label-Button-Button",
                        "wType": "FlexContainer"
                    },
                    "srcWgtKUID": "c3f47a8d57c84c8bb2030df71a79a16d",
                    "translateAtInstance": false
                }
            ]
        },
        "groups": {
            "apis": [],
            "events": [],
            "properties": [],
            "widgets": []
        },
        "properties": {
            "custom": [],
            "passthrough": [
                {
                    "access": "Enable",
                    "group": "General",
                    "kuid": "bdc818a5b5a540a8be2c6350835140dc",
                    "originalPropertyKey": "text",
                    "propertyIndex": 1,
                    "propertyKey": "icon",
                    "pw": {
                        "access": "readwrite",
                        "category": "look",
                        "dependencyConditions": {},
                        "dependentKeysKUIDs": null,
                        "displayName": "icom",
                        "isHiddenInTool": false,
                        "srcWidget": "lblIcon",
                        "type": "string",
                        "uiRepresentation": "Label-Textbox",
                        "wType": "Label"
                    },
                    "srcWgtKUID": "g49180ca4b2844b8b8c5566a97dc46c9"
                },
                {
                    "access": "Enable",
                    "group": "General",
                    "kuid": "c76c5a65a4c84847aae433ea10f348d2",
                    "originalPropertyKey": "text",
                    "propertyIndex": 2,
                    "propertyKey": "title",
                    "pw": {
                        "access": "readwrite",
                        "category": "look",
                        "dependencyConditions": {},
                        "dependentKeysKUIDs": null,
                        "displayName": "title",
                        "isHiddenInTool": false,
                        "srcWidget": "lblTitle",
                        "type": "string",
                        "uiRepresentation": "Label-Textbox",
                        "wType": "Label"
                    },
                    "srcWgtKUID": "a916b717dae948bd8d030624ebff6d50"
                }
            ]
        },
        "widgets": {
            "expose": [],
            "passthrough": []
        }
    },
    "namespace": "com.hcl.pgenelectricdemo",
    "version": "1.0.0"
}