{
    "DNDConfig": null,
    "_height_": {
        "type": "string",
        "value": "50dp"
    },
    "_left_": {
        "type": "string",
        "value": "0dp"
    },
    "_margin_": [
        0,
        0,
        0,
        0
    ],
    "_orientation_": 6,
    "_padding_": [
        0,
        0,
        0,
        0
    ],
    "_percent_": true,
    "_skin_": "sb9206d585f9447889968d5b3689fd67",
    "_top_": {
        "type": "string",
        "value": "3%"
    },
    "_width_": {
        "type": "string",
        "value": "150dp"
    },
    "allboxes": [],
    "autogrowmode": 0,
    "canUpdateUI": true,
    "centerx": {
        "type": "string",
        "value": "50%"
    },
    "children": [
        "lblStartCharge"
    ],
    "clipbounds": true,
    "containerweight": 100,
    "enablescrolling": true,
    "id": "flxStartCharge",
    "info": null,
    "iscustomlayout": false,
    "isvisible": true,
    "kuid": "e2f78ba349e44b09a314753c4d978aab",
    "layouttype": 2,
    "name": "kony.ui.FlexContainer",
    "parent": "flxContent",
    "pf": "frmCharge",
    "retaincontentalignment": false,
    "retainflexpositionproperties": false,
    "retainflowhorizontalalignment": false,
    "snapgridsize": 10,
    "snaptogrid": true,
    "wType": "FlexContainer",
    "widgetalignment": 1,
    "zindex": 1
}